design_kgex/__init__.py
design_kgex/design_knowledge.py
design_kgex/patent_text.py
design_kgex/supplementary.pkl
design_kgex-0.2.6.dist-info/LICENSE
design_kgex-0.2.6.dist-info/METADATA
design_kgex-0.2.6.dist-info/WHEEL
design_kgex-0.2.6.dist-info/dependency_links.txt
design_kgex-0.2.6.dist-info/top_level.txt
design_kgex-0.2.6.dist-info/RECORD
